pyrunjs/__init__.py
pyrunjs/runner.py
pyrunjs-0.1.7.dist-info/METADATA
pyrunjs-0.1.7.dist-info/WHEEL
pyrunjs-0.1.7.dist-info/top_level.txt
pyrunjs-0.1.7.dist-info/RECORD
