Metadata-Version: 2.1
Name: pyrunjs
Version: 0.1.7
Summary: Easily run javascript expressions using python.
Author-email: JoCarey1 <JoCarey@foxmail.com>
License: MIT
Requires-Python: >=3.8
